pymagery/__init__.py
pymagery-0.0.1.dist-info/METADATA
pymagery-0.0.1.dist-info/WHEEL
pymagery-0.0.1.dist-info/top_level.txt
pymagery-0.0.1.dist-info/RECORD
