Metadata-Version: 2.1
Name: pymagery
Version: 0.0.1
Summary: A library that assist with creating images
Home-page: https://sossinaydev.github.io/pypackages/imagery
Author: sossinayDev
Author-email: sossinayDev@gmail.com
Project-URL: Docs, https://sossinaydev.github.io/pypackages/imagery
Classifier: Programming Language :: Python :: 3
Classifier: License :: OSI Approved :: MIT License
Classifier: Operating System :: OS Independent
Requires-Python: >=3.6
